dfhir/__init__.py
dfhir/accounts/__init__.py
dfhir/accounts/admin.py
dfhir/accounts/apps.py
dfhir/accounts/choices.py
dfhir/accounts/migrations/0001_initial.py
dfhir/accounts/migrations/0002_initial.py
dfhir/accounts/migrations/0003_initial.py
dfhir/accounts/migrations/0004_initial.py
dfhir/accounts/migrations/0005_alter_accountcoverage_coverage.py
dfhir/accounts/migrations/__init__.py
dfhir/accounts/models.py
dfhir/accounts/serializers.py
dfhir/accounts/urls.py
dfhir/accounts/views.py
dfhir/activitydefinitions/__init__.py
dfhir/activitydefinitions/admin.py
dfhir/activitydefinitions/apps.py
dfhir/activitydefinitions/choices.py
dfhir/activitydefinitions/migrations/0001_initial.py
dfhir/activitydefinitions/migrations/0002_initial.py
dfhir/activitydefinitions/migrations/0003_initial.py
dfhir/activitydefinitions/migrations/0004_initial.py
dfhir/activitydefinitions/migrations/0005_initial.py
dfhir/activitydefinitions/migrations/0006_initial.py
dfhir/activitydefinitions/migrations/0007_initial.py
dfhir/activitydefinitions/migrations/0008_initial.py
dfhir/activitydefinitions/migrations/0009_initial.py
dfhir/activitydefinitions/migrations/0010_activityplandefinitionreference.py
dfhir/activitydefinitions/migrations/0011_alter_activitydefinition_kind.py
dfhir/activitydefinitions/migrations/0012_rename_activityplandefinitionreference_activitydefinitionplandefinitionreference.py
dfhir/activitydefinitions/migrations/0013_activitydefinitionplandefinitioncodeablereference.py
dfhir/activitydefinitions/migrations/__init__.py
dfhir/activitydefinitions/models.py
dfhir/activitydefinitions/serializers.py
dfhir/activitydefinitions/urls.py
dfhir/activitydefinitions/views.py
dfhir/adverseevents/__init__.py
dfhir/adverseevents/admin.py
dfhir/adverseevents/apps.py
dfhir/adverseevents/choices.py
dfhir/adverseevents/migrations/0001_initial.py
dfhir/adverseevents/migrations/0002_initial.py
dfhir/adverseevents/migrations/0003_initial.py
dfhir/adverseevents/migrations/0004_initial.py
dfhir-0.1.0a21.dist-info/METADATA
dfhir-0.1.0a21.dist-info/WHEEL
dfhir-0.1.0a21.dist-info/RECORD
